{"fname":"daily.journal.2023.03","stub":true,"vault":{"fsPath":"vault"},"schemaStub":false,"type":"note","updated":1735913551693,"created":1735913551693,"id":"0dcvkviy4rrh0ay2usmajue","desc":"","links":[],"anchors":{},"children":["1uoml3dpen7vb528wa5pbw1","282ig15cflovkyb5g4bdsp0","o4m6hv1uum0gy7q1sgddmlh","lbja30b6220704og4w9hwjq","vshou6d27ciywghbghf3zzc","bwr5emsl34aisoum3hyhdsd","8620kisf48l0i96i6ycbejn","fietuww1zl2s1098sgn6psk"],"parent":"v7t3cdwtijxi2zkslak5zzb","data":{},"title":"03","schema":{"schemaId":"w8dn79kjze2evvr424leu2s","moduleId":"daily"}}
