{"fname":"daily.journal.2023","stub":true,"vault":{"fsPath":"vault"},"schemaStub":false,"type":"note","updated":1737905688626,"created":1737905688626,"id":"a30p1u3cevdmsgqv0be2jsj","desc":"","links":[],"anchors":{},"children":["i5mkdwu332ma1bbjqwx9r5e","mo7hsill7w11c8zar9y580p","izzjpy29r6kh0748lwq0hz1","bi2rotwlnd5vx7w6mrmovy2","omb4g04ptjaqfmtp7qudhe5","lfhct75dveafvqb3ck6jb3s","odrw0gpxxg0lb6uska0gxra","7gmopy6zf8z6i5w5cz3i7kh","poanid951zrgtw4y0qpdfdr"],"parent":"erx1s6gl8w1h0rd8m5cwmv6","data":{},"title":"2023","schema":{"schemaId":"vj6bugqpfrtg4wzcb78jk3h","moduleId":"daily"}}
