{"id":"bi0m1k6xhoc784lseu3w05j","title":"2022-09-24","desc":"","updated":1664027483304,"created":1664027376195,"traitIds":["journalNote"],"custom":{},"fname":"daily.journal.2022.09.24","type":"note","vault":{"fsPath":"vault"},"contentHash":"76cdac97c1036a75dfa6bf1469ef2653","links":[{"type":"wiki","from":{"fname":"daily.journal.2022.09.24","id":"bi0m1k6xhoc784lseu3w05j","vaultName":"vault"},"value":"books.zero-to-sold","position":{"start":{"line":2,"column":24,"offset":24},"end":{"line":2,"column":46,"offset":46},"indent":[]},"xvault":false,"sameFile":false,"to":{"fname":"books.zero-to-sold"}}],"anchors":{},"children":[],"parent":"p1b7hl3licofyj6zmw5alfv","data":{},"schema":{"schemaId":"0sn79enyq0v7bst9s8ei8hx","moduleId":"daily"}}
