{"id":"NymnTTPRLL8GPcJcFy3uA","title":"Land redistribution after Partition","desc":"","updated":1642956906318,"created":1616188913148,"custom":{},"fname":"history.india.land_redistribution_after_partition","type":"note","vault":{"fsPath":"vault"},"contentHash":"768f16e86347e1d05ccc601dba61c0cd","links":[{"type":"wiki","from":{"fname":"history.india.land_redistribution_after_partition","id":"NymnTTPRLL8GPcJcFy3uA","vaultName":"vault"},"value":"history.india.refugee_crisis_after_partition","alias":"refugee crisis","position":{"start":{"line":5,"column":5,"offset":330},"end":{"line":5,"column":70,"offset":395},"indent":[]},"xvault":false,"sameFile":false,"to":{"fname":"history.india.refugee_crisis_after_partition"}},{"type":"wiki","from":{"fname":"history.india.land_redistribution_after_partition","id":"NymnTTPRLL8GPcJcFy3uA","vaultName":"vault"},"value":"history.india.standard_acre","alias":"Standard acre","position":{"start":{"line":9,"column":32,"offset":584},"end":{"line":9,"column":80,"offset":632},"indent":[]},"xvault":false,"sameFile":false,"to":{"fname":"history.india.standard_acre"}},{"type":"wiki","from":{"fname":"history.india.land_redistribution_after_partition","id":"NymnTTPRLL8GPcJcFy3uA","vaultName":"vault"},"value":"history.india.graded_cut","alias":"Graded Cut","position":{"start":{"line":10,"column":1,"offset":637},"end":{"line":10,"column":43,"offset":679},"indent":[]},"xvault":false,"sameFile":false,"to":{"fname":"history.india.graded_cut"}},{"from":{"fname":"history.india.graded_cut","id":"TDP7mJHkunud0043OESoI","vaultName":"vault"},"type":"backlink","position":{"start":{"line":3,"column":1,"offset":32},"end":{"line":3,"column":70,"offset":101},"indent":[]},"value":"history.india.land_redistribution_after_partition"},{"from":{"fname":"history.india.refugee_crisis_after_partition","id":"a60e0740-e1b0-47fc-91f6-6d101cd82397","vaultName":"vault"},"type":"backlink","position":{"start":{"line":10,"column":25,"offset":486},"end":{"line":10,"column":126,"offset":587},"indent":[]},"value":"history.india.land_redistribution_after_partition"}],"anchors":{},"children":[],"parent":"x6V2SrfdyeC4Vo1AJ643s","data":{}}
